{"title":"Transform Data","markdown":{"yaml":{"title":"Transform Data"},"headingText":"Setup","containsRefs":false,"markdown":"\n\n\n### Packages\n\n```{r setup}\nsuppressPackageStartupMessages({\n  library(tidyverse)\n  library(tidync)\n  library(data.table)\n  library(sf)\n  library(arrow)\n  library(units)\n\n})\n```\n\n### Climate Periods\n\n```{r climate-periods}\n\n# Climatological Standard Reference Period Normals\ncrp_beg <- 1961\ncrp_end <- 1990\ncrp_lbl <- paste(\"CRP \", crp_beg, \"-\", crp_end, sep = \"\")\n\n# Climatological Period Average\ncpa_beg <- 2011\ncpa_end <- 2020\ncpa_lbl <- paste(\"CPA \", cpa_beg, \"-\", cpa_end, sep = \"\")\n```\n\n### Paths\n\n```{r paths}\ndir_download <- \"_data/1-download/\"\ndir_transform <- \"_data/2-transform/\"\n```\n\n## Transform data\n\n### Transform land sea mask\n\n```{r transform-land-sea-mask}\n\nfn_transform_land_sea_mask <- function(dir_download) {\n\n  fil <- \"land-sea-mask.nc\"\n  pth <- paste(dir_download, fil, sep = \"\")\n  nc <- tidync(pth)\n\n  df <- nc |>\n    hyper_tibble() |>\n    as_tibble() |> # tidyverse data frame\n    rename(lon = longitude, lat = latitude) |>\n    mutate(\n      lon = as.numeric(lon),\n      lat = as.numeric(lat),\n      lsm = as.integer(round(lsm))\n    ) |>\n    select(lon, lat, lsm) |> # drop all other columns\n    arrange(lon, lat)\n  return(df)\n}\n\ndir <- dir_transform\nfil <- \"land-sea-mask.parquet\"\npth <- paste(dir, fil, sep = \"\")\n\nif (!file.exists(pth))  {\n  land_sea_mask_df <- fn_transform_land_sea_mask(dir_download)\n  write_parquet(land_sea_mask_df, pth)\n} else {\n  land_sea_mask_df <- read_parquet(pth)\n}\n\n```\n\n### Transform global coastline\n\n```{r transform-global-coastline}\n\nfn_transform_global_coastline <- function(dir_download) {\n  # Create a single coastline multiline, making sure geometries are valid\n  # (eliminates extra horizontal line on map)\n\n  fil <- \"global-coastline.gpkg\"\n  pth <- paste(dir_download, fil, sep = \"\")\n  coastline_sf <- st_read(pth, quiet = TRUE)\n\n  coastline_sf <- coastline_sf |>\n    select(geom) |>\n    mutate(id = \"world\") |>\n    group_by(id) |>\n    st_make_valid() |>\n    summarise()\n  return(coastline_sf)\n}\n\ndir <- dir_transform\nfil <- \"global-coastline.gpkg\"\npth <- paste(dir, fil, sep = \"\")\n\nif (!file.exists(pth))  {\n  coastline_sf <- fn_transform_global_coastline(dir_download)\n  st_write(coastline_sf, pth, delete_dsn = TRUE, quiet = TRUE)\n} else {\n  coastline_sf <- st_read(pth, quiet=TRUE)\n}\n\n```\n\n### Read NetCDF climate data\n\n```{r read-nc-chunk}\n\nfn_read_nc_chunk <- function(dt, var, vnm, start, stop, ncs_df) {\n\n  setnames(dt, old = \"longitude\", new = \"lon\")\n  setnames(dt, old = \"latitude\", new = \"lat\")\n  setnames(dt, old = vnm, new = var)\n\n  dt[, lon := as.numeric(lon)]\n  dt[, lat := as.numeric(lat)]\n  dt[lon > 180, lon := lon - 360]\n\n  dt[, mth := as.integer(substr(valid_time, 6, 7))]\n  setDT(dt)\n\n  # add row before grouping\n  cv <- vnm\n  if (var == \"t\") {\n    avgcv <- round(mean(dt$t) - 273.15, 3)\n    maxcv <- round(max(dt$t) - 273.15, 3)\n    mincv <- round(min(dt$t) - 273.15, 3)\n    maxdate <- max(dt$valid_time)\n    mindate <- min(dt$valid_time)\n  } else {\n    avgcv <- round(mean(dt$p) * 1000, 3)\n    maxcv <- round(max(dt$p) * 1000, 3)\n    mincv <- round(min(dt$p) * 1000, 3)\n    maxdate <- substr(max(dt$valid_time), 1, 10)\n    mindate <- substr(min(dt$valid_time), 1, 10)\n  }\n  maxlon <- max(dt$lon)\n  minlon <- min(dt$lon)\n  maxlat <- max(dt$lat)\n  minlat <- min(dt$lat)\n  datapts <- nrow(dt)\n\n  new_row <- list(\n    cv = cv,\n    avgcv   = avgcv,\n    maxcv   = maxcv,\n    mincv   = mincv,\n    maxdate = maxdate,\n    mindate = mindate,\n    maxlon  = maxlon,\n    minlon  = minlon,\n    maxlat  = maxlat,\n    minlat  = minlat,\n    datapts = datapts\n  )\n\n  ncs_df <- rbind(ncs_df, new_row)\n\n  if (var == \"t\") {\n    drop <- setdiff(names(dt), c(\"lon\", \"lat\", \"mth\", \"t\"))\n    dt[, (drop) := NULL]\n    dt <- dt[, .(t = sum(t, na.rm = TRUE)), by = .(lon, lat, mth)]\n  } else {\n    drop <- setdiff(names(dt), c(\"lon\", \"lat\", \"mth\", \"p\"))\n    dt[, (drop) := NULL]\n    dt <- dt[, .(p = sum(p, na.rm = TRUE)), by = .(lon, lat, mth)]\n  }\n  setDT(dt)\n  gc()\n\n  return(list(dt, ncs_df))\n}\n\n```\n\n```{r read-nc}\nfn_read_nc <- function(pth, var, vnm, ncs_df) {\n  nc <- tidync(pth)\n\n  dims <- nc |> activate(vnm) |> hyper_dims()\n  ntime <- dims |> filter(name == \"valid_time\") |> pull(length)\n  chunk <- 60L\n\n  print(paste(\"chunk size \", chunk))\n\n  for (start in seq(1L, ntime, by = chunk)) {\n    chnk_beg <- Sys.time()\n    stop <- min(start + chunk - 1L, ntime)\n\n    chunk_dt <- nc |>\n      hyper_filter(valid_time = index %in% start:stop) |>\n      hyper_tibble(select_var = vnm) |>\n      as.data.table()\n\n\n    result <- fn_read_nc_chunk(chunk_dt, var, vnm, start, stop, ncs_df)\n    chunk_grp_dt <- result[[1]]\n    ncs_df <- result[[2]]\n\n    if (start == 1L) {\n      dt <- chunk_grp_dt\n    } else {\n      dt <- rbindlist(list(dt, chunk_grp_dt))\n      # group\n      if (var == \"t\") {\n        dt <- dt[, .(t = sum(t, na.rm = TRUE)), by = .(lon, lat, mth)]\n      } else {\n        dt <- dt[, .(p = sum(p, na.rm = TRUE)), by = .(lon, lat, mth)]\n      }\n    }\n    chnk_end <- Sys.time()\n    print(paste(\"chunk time: \", (chnk_end - chnk_beg)))\n  }\n\n  return(list(dt, ncs_df))\n}\n\n```\n\n```{r get-t-data}\n\nfn_get_t_data <- function(dir, cp, ncs_df) {\n\n  cv <- \"t\"\n  vnm <- \"t2m\"\n  fil <- paste(cp, \"-era5-\", cv, \".nc\", sep = \"\")\n  pth <- paste(dir, fil, sep = \"\")\n  result <- fn_read_nc(pth, cv, vnm, ncs_df)\n  t_dt <- result[[1]]\n  ncs_df <- result[[2]]\n\n  setorder(t_dt, lon, lat, mth)\n  setDT(t_dt)\n\n  # convert from sum to avg\n  yrs <- ifelse(cp == \"crp\", 30, 10)\n  t_dt[, t := t / yrs]\n\n  # convert from kelvin to celsius\n  t_dt[, t := t - 273.15]\n\n  return(list(t_dt, ncs_df))\n}\n```\n\n```{r get-p-data}\n\nfn_get_p_data <- function(dir, cp, ncs_df) {\n\n  ndy <- data.table(\n    mth = 1:12,\n    ndays = as.integer(c(31, 28, 31, 30, 31, 30, 31, 31, 30, 31, 30, 31))\n  )\n\n  cv <- \"p\"\n  vnm <- \"tp\"\n  fil <- paste(cp, \"-era5-\", cv, \".nc\", sep = \"\")\n  pth <- paste(dir, fil, sep = \"\")\n  result <- fn_read_nc(pth, cv, vnm, ncs_df)\n  p_dt <- result[[1]]\n  ncs_df <- result[[2]]\n\n  setorder(p_dt, lon, lat, mth)\n  setDT(p_dt)\n\n  # convert from sum to avg\n  yrs <- ifelse(cp == \"crp\", 30, 10)\n  p_dt[, p := p / yrs]\n\n  # add number of days using lookup table\n  p_dt[ndy, ndy := i.ndays, on = \"mth\"]\n  p_dt[, p := p * ndy * 1000]\n  p_dt[, ndy := NULL]\n\n  return(list(p_dt, ncs_df))\n\n}\n```\n\n### Transform NetCDF climate data\n\n```{r transform-t-data, cp}\n\nfn_transform_t_data <- function(t_dt) {\n\n  # pivot and calculate stats\n\n  t_wide_dt <- t_dt |>\n    pivot_wider(\n      names_from = c(mth),\n      values_from = c(\"t\"),\n      names_prefix = \"t\",\n      names_sep = \"\" # no underscore in new col names\n    )\n\n  tcols <- paste0(\"t\", 1:12)\n  t_stats_dt <- t_wide_dt |>\n    mutate(\n      tavg = (t1 + t2 + t3 + t4 + t5 + t6 + t7 + t8 + t9 + t10 + t11 + t12) /\n        12,\n      tmax = pmax(t1, t2, t3, t4, t5, t6, t7, t8, t9, t10, t11, t12),\n      tmin = pmin(t1, t2, t3, t4, t5, t6, t7, t8, t9, t10, t11, t12),\n      totm = (t1 + t2 + t3 + t10 + t11 + t12) / 6,\n      tats = (t4 + t5 + t6 + t7 + t8 + t9) / 6,\n      tg10 = rowSums(across(all_of(tcols), ~ .x >= 10))\n    )\n  t_stats_df <- t_stats_dt |>\n    select(-t1, -t2, -t3, -t4, -t5, -t6, -t7, -t8, -t9, -t10, -t11, -t12)\n\n  return(t_stats_df)\n}\n\n```\n\n```{r transform-p-data}\n\nfn_transform_p_data <- function(p_dt) {\n\n  # pivot and calculate stats\n\n  p_wide_dt <- p_dt |>\n    pivot_wider(\n      names_from = c(mth),\n      values_from = c(\"p\"),\n      names_prefix = \"p\",\n      names_sep = \"\" # no underscore in new col names\n    )\n  \n  pcols <- paste0(\"p\", 1:12)\n  p_stats_dt <- p_wide_dt |>\n    mutate(\n      ptot = (p1 + p2 + p3 + p4 + p5 + p6 + p7 + p8 + p9 + p10 + p11 + p12),\n      pmax = pmax(p1, p2, p3, p4, p5, p6, p7, p8, p9, p10, p11, p12),\n      pmin = pmin(p1, p2, p3, p4, p5, p6, p7, p8, p9, p10, p11, p12),\n      pavg = ptot / 12,\n      potm = (p1 + p2 + p3 + p10 + p11 + p12),\n      pats = (p4 + p5 + p6 + p7 + p8 + p9),\n      pmno = pmin(p10, p11, p12, p1, p2, p3),\n      pmxo = pmax(p10, p11, p12, p1, p2, p3),\n      pmna = pmin(p4, p5, p6, p7, p8, p9),\n      pmxa = pmax(p4, p5, p6, p7, p8, p9),\n      pl60 = rowSums(across(all_of(pcols), ~ .x < 60))\n    )\n  p_stats_df <- p_stats_dt |>\n    select(-p1, -p2, -p3, -p4, -p5, -p6, -p7, -p8, -p9, -p10, -p11, -p12)\n\n  return(p_stats_df)\n\n}\n\n```\n\n### Calculate grid cell area\n\n```{r calc-grid-area}\n\nfn_calc_area <- function(df) {\n  earth_radius_km <- 6371\n  lat_grid_degrees <- 0.25\n  lon_grid_degrees <- 0.25\n  area_df <- df |>\n    mutate(\n      lat_radians = lat * pi / 180,\n      lat_grid_radians = lat_grid_degrees * pi / 180,\n      lon_grid_radians = lon_grid_degrees * pi / 180,\n      # cell area in km^2\n      area = (earth_radius_km^2 *\n        lon_grid_radians *\n        (sin(lat_radians + lat_grid_radians / 2) -\n          sin(lat_radians - lat_grid_radians / 2))) /\n        1e6\n    ) |>\n    select(-lat_radians, -lat_grid_radians, -lon_grid_radians) |>\n    select(lat, lon, area, lsm, everything())\n  return(area_df)\n\n}\n```\n\n### Save transformed climate data\n\n```{r save-climate-data}\n\nfn_create_ncs_df <- function() {\n  ncs_df <- data.frame(\n    cv      = character(),\n    avgcv   = numeric(),\n    maxcv   = numeric(),\n    mincv   = numeric(),\n    maxdate = character(),\n    mindate = character(),\n    maxlon  = numeric(),\n    minlon  = numeric(),\n    maxlat  = numeric(),\n    minlat  = numeric(),\n    datapts = numeric()\n  )\n  return(ncs_df)\n}\n\nfn_save_climate_data <- function (dir_read, dir_save, cp, ncs_df) {\n \n  result <- fn_get_t_data(dir_read, cp, ncs_df)\n  t_dt <- result[[1]]\n  ncs_df <- result[[2]]\n  pth <- paste(dir_save, cp, \"-monthly-data-t.parquet\", sep = \"\")\n  write_parquet(t_dt, pth)\n\n  result <- fn_get_p_data(dir_read, cp, ncs_df)\n  p_dt <- result[[1]]\n  ncs_df <- result[[2]]\n  pth <- paste(dir_save, cp, \"-monthly-data-p.parquet\", sep = \"\")\n  write_parquet(p_dt, pth)\n\n  pth <- paste(dir_save, cp, \"-nc-summary.csv\", sep = \"\")\n  write_csv(ncs_df, pth)\n\n  t_stats_df <- fn_transform_t_data(t_dt)\n  pth <- paste(dir_save, cp, \"-average-stats-t.parquet\", sep = \"\")\n  write_parquet(t_stats_df, pth)\n\n  p_stats_df <- fn_transform_p_data(p_dt)\n  pth <- paste(dir_save, cp, \"-average-stats-p.parquet\", sep = \"\")\n  write_parquet(p_stats_df, pth)\n\n  j1_df <- inner_join(t_stats_df, p_stats_df, by = c(\"lon\", \"lat\"))\n  j2_df <- inner_join(j1_df, land_sea_mask_df, by = c(\"lon\", \"lat\"))\n  cn_df <- fn_calc_area(j2_df)\n  pth <- paste(dir_save, cp, \"-climate-normals.parquet\", sep = \"\")\n  write_parquet(cn_df, pth)\n\n}\n\ndir_read <- dir_download\ndir_save <- dir_transform\n\ncp <- \"cpa\"\npth <- paste(dir_save, cp, \"-climate-normals.parquet\", sep = \"\")\n# only need to read, transform, and save if file doesn't exist\nif (!file.exists(pth)) {\n  ncs_df <- fn_create_ncs_df()\n  fn_save_climate_data(dir_read, dir_save, cp, ncs_df) \n}\n\ncp <- \"crp\"\npth <- paste(dir_save, cp, \"-climate-normals.parquet\", sep = \"\")\n# only need to read, transform, and save if file doesn't exist\nif (!file.exists(pth)) {\n  ncs_df <- fn_create_ncs_df()\n  fn_save_climate_data(dir_read, dir_save, cp, ncs_df)  \n}\n\n```\n","srcMarkdownNoYaml":"\n\n## Setup\n\n### Packages\n\n```{r setup}\nsuppressPackageStartupMessages({\n  library(tidyverse)\n  library(tidync)\n  library(data.table)\n  library(sf)\n  library(arrow)\n  library(units)\n\n})\n```\n\n### Climate Periods\n\n```{r climate-periods}\n\n# Climatological Standard Reference Period Normals\ncrp_beg <- 1961\ncrp_end <- 1990\ncrp_lbl <- paste(\"CRP \", crp_beg, \"-\", crp_end, sep = \"\")\n\n# Climatological Period Average\ncpa_beg <- 2011\ncpa_end <- 2020\ncpa_lbl <- paste(\"CPA \", cpa_beg, \"-\", cpa_end, sep = \"\")\n```\n\n### Paths\n\n```{r paths}\ndir_download <- \"_data/1-download/\"\ndir_transform <- \"_data/2-transform/\"\n```\n\n## Transform data\n\n### Transform land sea mask\n\n```{r transform-land-sea-mask}\n\nfn_transform_land_sea_mask <- function(dir_download) {\n\n  fil <- \"land-sea-mask.nc\"\n  pth <- paste(dir_download, fil, sep = \"\")\n  nc <- tidync(pth)\n\n  df <- nc |>\n    hyper_tibble() |>\n    as_tibble() |> # tidyverse data frame\n    rename(lon = longitude, lat = latitude) |>\n    mutate(\n      lon = as.numeric(lon),\n      lat = as.numeric(lat),\n      lsm = as.integer(round(lsm))\n    ) |>\n    select(lon, lat, lsm) |> # drop all other columns\n    arrange(lon, lat)\n  return(df)\n}\n\ndir <- dir_transform\nfil <- \"land-sea-mask.parquet\"\npth <- paste(dir, fil, sep = \"\")\n\nif (!file.exists(pth))  {\n  land_sea_mask_df <- fn_transform_land_sea_mask(dir_download)\n  write_parquet(land_sea_mask_df, pth)\n} else {\n  land_sea_mask_df <- read_parquet(pth)\n}\n\n```\n\n### Transform global coastline\n\n```{r transform-global-coastline}\n\nfn_transform_global_coastline <- function(dir_download) {\n  # Create a single coastline multiline, making sure geometries are valid\n  # (eliminates extra horizontal line on map)\n\n  fil <- \"global-coastline.gpkg\"\n  pth <- paste(dir_download, fil, sep = \"\")\n  coastline_sf <- st_read(pth, quiet = TRUE)\n\n  coastline_sf <- coastline_sf |>\n    select(geom) |>\n    mutate(id = \"world\") |>\n    group_by(id) |>\n    st_make_valid() |>\n    summarise()\n  return(coastline_sf)\n}\n\ndir <- dir_transform\nfil <- \"global-coastline.gpkg\"\npth <- paste(dir, fil, sep = \"\")\n\nif (!file.exists(pth))  {\n  coastline_sf <- fn_transform_global_coastline(dir_download)\n  st_write(coastline_sf, pth, delete_dsn = TRUE, quiet = TRUE)\n} else {\n  coastline_sf <- st_read(pth, quiet=TRUE)\n}\n\n```\n\n### Read NetCDF climate data\n\n```{r read-nc-chunk}\n\nfn_read_nc_chunk <- function(dt, var, vnm, start, stop, ncs_df) {\n\n  setnames(dt, old = \"longitude\", new = \"lon\")\n  setnames(dt, old = \"latitude\", new = \"lat\")\n  setnames(dt, old = vnm, new = var)\n\n  dt[, lon := as.numeric(lon)]\n  dt[, lat := as.numeric(lat)]\n  dt[lon > 180, lon := lon - 360]\n\n  dt[, mth := as.integer(substr(valid_time, 6, 7))]\n  setDT(dt)\n\n  # add row before grouping\n  cv <- vnm\n  if (var == \"t\") {\n    avgcv <- round(mean(dt$t) - 273.15, 3)\n    maxcv <- round(max(dt$t) - 273.15, 3)\n    mincv <- round(min(dt$t) - 273.15, 3)\n    maxdate <- max(dt$valid_time)\n    mindate <- min(dt$valid_time)\n  } else {\n    avgcv <- round(mean(dt$p) * 1000, 3)\n    maxcv <- round(max(dt$p) * 1000, 3)\n    mincv <- round(min(dt$p) * 1000, 3)\n    maxdate <- substr(max(dt$valid_time), 1, 10)\n    mindate <- substr(min(dt$valid_time), 1, 10)\n  }\n  maxlon <- max(dt$lon)\n  minlon <- min(dt$lon)\n  maxlat <- max(dt$lat)\n  minlat <- min(dt$lat)\n  datapts <- nrow(dt)\n\n  new_row <- list(\n    cv = cv,\n    avgcv   = avgcv,\n    maxcv   = maxcv,\n    mincv   = mincv,\n    maxdate = maxdate,\n    mindate = mindate,\n    maxlon  = maxlon,\n    minlon  = minlon,\n    maxlat  = maxlat,\n    minlat  = minlat,\n    datapts = datapts\n  )\n\n  ncs_df <- rbind(ncs_df, new_row)\n\n  if (var == \"t\") {\n    drop <- setdiff(names(dt), c(\"lon\", \"lat\", \"mth\", \"t\"))\n    dt[, (drop) := NULL]\n    dt <- dt[, .(t = sum(t, na.rm = TRUE)), by = .(lon, lat, mth)]\n  } else {\n    drop <- setdiff(names(dt), c(\"lon\", \"lat\", \"mth\", \"p\"))\n    dt[, (drop) := NULL]\n    dt <- dt[, .(p = sum(p, na.rm = TRUE)), by = .(lon, lat, mth)]\n  }\n  setDT(dt)\n  gc()\n\n  return(list(dt, ncs_df))\n}\n\n```\n\n```{r read-nc}\nfn_read_nc <- function(pth, var, vnm, ncs_df) {\n  nc <- tidync(pth)\n\n  dims <- nc |> activate(vnm) |> hyper_dims()\n  ntime <- dims |> filter(name == \"valid_time\") |> pull(length)\n  chunk <- 60L\n\n  print(paste(\"chunk size \", chunk))\n\n  for (start in seq(1L, ntime, by = chunk)) {\n    chnk_beg <- Sys.time()\n    stop <- min(start + chunk - 1L, ntime)\n\n    chunk_dt <- nc |>\n      hyper_filter(valid_time = index %in% start:stop) |>\n      hyper_tibble(select_var = vnm) |>\n      as.data.table()\n\n\n    result <- fn_read_nc_chunk(chunk_dt, var, vnm, start, stop, ncs_df)\n    chunk_grp_dt <- result[[1]]\n    ncs_df <- result[[2]]\n\n    if (start == 1L) {\n      dt <- chunk_grp_dt\n    } else {\n      dt <- rbindlist(list(dt, chunk_grp_dt))\n      # group\n      if (var == \"t\") {\n        dt <- dt[, .(t = sum(t, na.rm = TRUE)), by = .(lon, lat, mth)]\n      } else {\n        dt <- dt[, .(p = sum(p, na.rm = TRUE)), by = .(lon, lat, mth)]\n      }\n    }\n    chnk_end <- Sys.time()\n    print(paste(\"chunk time: \", (chnk_end - chnk_beg)))\n  }\n\n  return(list(dt, ncs_df))\n}\n\n```\n\n```{r get-t-data}\n\nfn_get_t_data <- function(dir, cp, ncs_df) {\n\n  cv <- \"t\"\n  vnm <- \"t2m\"\n  fil <- paste(cp, \"-era5-\", cv, \".nc\", sep = \"\")\n  pth <- paste(dir, fil, sep = \"\")\n  result <- fn_read_nc(pth, cv, vnm, ncs_df)\n  t_dt <- result[[1]]\n  ncs_df <- result[[2]]\n\n  setorder(t_dt, lon, lat, mth)\n  setDT(t_dt)\n\n  # convert from sum to avg\n  yrs <- ifelse(cp == \"crp\", 30, 10)\n  t_dt[, t := t / yrs]\n\n  # convert from kelvin to celsius\n  t_dt[, t := t - 273.15]\n\n  return(list(t_dt, ncs_df))\n}\n```\n\n```{r get-p-data}\n\nfn_get_p_data <- function(dir, cp, ncs_df) {\n\n  ndy <- data.table(\n    mth = 1:12,\n    ndays = as.integer(c(31, 28, 31, 30, 31, 30, 31, 31, 30, 31, 30, 31))\n  )\n\n  cv <- \"p\"\n  vnm <- \"tp\"\n  fil <- paste(cp, \"-era5-\", cv, \".nc\", sep = \"\")\n  pth <- paste(dir, fil, sep = \"\")\n  result <- fn_read_nc(pth, cv, vnm, ncs_df)\n  p_dt <- result[[1]]\n  ncs_df <- result[[2]]\n\n  setorder(p_dt, lon, lat, mth)\n  setDT(p_dt)\n\n  # convert from sum to avg\n  yrs <- ifelse(cp == \"crp\", 30, 10)\n  p_dt[, p := p / yrs]\n\n  # add number of days using lookup table\n  p_dt[ndy, ndy := i.ndays, on = \"mth\"]\n  p_dt[, p := p * ndy * 1000]\n  p_dt[, ndy := NULL]\n\n  return(list(p_dt, ncs_df))\n\n}\n```\n\n### Transform NetCDF climate data\n\n```{r transform-t-data, cp}\n\nfn_transform_t_data <- function(t_dt) {\n\n  # pivot and calculate stats\n\n  t_wide_dt <- t_dt |>\n    pivot_wider(\n      names_from = c(mth),\n      values_from = c(\"t\"),\n      names_prefix = \"t\",\n      names_sep = \"\" # no underscore in new col names\n    )\n\n  tcols <- paste0(\"t\", 1:12)\n  t_stats_dt <- t_wide_dt |>\n    mutate(\n      tavg = (t1 + t2 + t3 + t4 + t5 + t6 + t7 + t8 + t9 + t10 + t11 + t12) /\n        12,\n      tmax = pmax(t1, t2, t3, t4, t5, t6, t7, t8, t9, t10, t11, t12),\n      tmin = pmin(t1, t2, t3, t4, t5, t6, t7, t8, t9, t10, t11, t12),\n      totm = (t1 + t2 + t3 + t10 + t11 + t12) / 6,\n      tats = (t4 + t5 + t6 + t7 + t8 + t9) / 6,\n      tg10 = rowSums(across(all_of(tcols), ~ .x >= 10))\n    )\n  t_stats_df <- t_stats_dt |>\n    select(-t1, -t2, -t3, -t4, -t5, -t6, -t7, -t8, -t9, -t10, -t11, -t12)\n\n  return(t_stats_df)\n}\n\n```\n\n```{r transform-p-data}\n\nfn_transform_p_data <- function(p_dt) {\n\n  # pivot and calculate stats\n\n  p_wide_dt <- p_dt |>\n    pivot_wider(\n      names_from = c(mth),\n      values_from = c(\"p\"),\n      names_prefix = \"p\",\n      names_sep = \"\" # no underscore in new col names\n    )\n  \n  pcols <- paste0(\"p\", 1:12)\n  p_stats_dt <- p_wide_dt |>\n    mutate(\n      ptot = (p1 + p2 + p3 + p4 + p5 + p6 + p7 + p8 + p9 + p10 + p11 + p12),\n      pmax = pmax(p1, p2, p3, p4, p5, p6, p7, p8, p9, p10, p11, p12),\n      pmin = pmin(p1, p2, p3, p4, p5, p6, p7, p8, p9, p10, p11, p12),\n      pavg = ptot / 12,\n      potm = (p1 + p2 + p3 + p10 + p11 + p12),\n      pats = (p4 + p5 + p6 + p7 + p8 + p9),\n      pmno = pmin(p10, p11, p12, p1, p2, p3),\n      pmxo = pmax(p10, p11, p12, p1, p2, p3),\n      pmna = pmin(p4, p5, p6, p7, p8, p9),\n      pmxa = pmax(p4, p5, p6, p7, p8, p9),\n      pl60 = rowSums(across(all_of(pcols), ~ .x < 60))\n    )\n  p_stats_df <- p_stats_dt |>\n    select(-p1, -p2, -p3, -p4, -p5, -p6, -p7, -p8, -p9, -p10, -p11, -p12)\n\n  return(p_stats_df)\n\n}\n\n```\n\n### Calculate grid cell area\n\n```{r calc-grid-area}\n\nfn_calc_area <- function(df) {\n  earth_radius_km <- 6371\n  lat_grid_degrees <- 0.25\n  lon_grid_degrees <- 0.25\n  area_df <- df |>\n    mutate(\n      lat_radians = lat * pi / 180,\n      lat_grid_radians = lat_grid_degrees * pi / 180,\n      lon_grid_radians = lon_grid_degrees * pi / 180,\n      # cell area in km^2\n      area = (earth_radius_km^2 *\n        lon_grid_radians *\n        (sin(lat_radians + lat_grid_radians / 2) -\n          sin(lat_radians - lat_grid_radians / 2))) /\n        1e6\n    ) |>\n    select(-lat_radians, -lat_grid_radians, -lon_grid_radians) |>\n    select(lat, lon, area, lsm, everything())\n  return(area_df)\n\n}\n```\n\n### Save transformed climate data\n\n```{r save-climate-data}\n\nfn_create_ncs_df <- function() {\n  ncs_df <- data.frame(\n    cv      = character(),\n    avgcv   = numeric(),\n    maxcv   = numeric(),\n    mincv   = numeric(),\n    maxdate = character(),\n    mindate = character(),\n    maxlon  = numeric(),\n    minlon  = numeric(),\n    maxlat  = numeric(),\n    minlat  = numeric(),\n    datapts = numeric()\n  )\n  return(ncs_df)\n}\n\nfn_save_climate_data <- function (dir_read, dir_save, cp, ncs_df) {\n \n  result <- fn_get_t_data(dir_read, cp, ncs_df)\n  t_dt <- result[[1]]\n  ncs_df <- result[[2]]\n  pth <- paste(dir_save, cp, \"-monthly-data-t.parquet\", sep = \"\")\n  write_parquet(t_dt, pth)\n\n  result <- fn_get_p_data(dir_read, cp, ncs_df)\n  p_dt <- result[[1]]\n  ncs_df <- result[[2]]\n  pth <- paste(dir_save, cp, \"-monthly-data-p.parquet\", sep = \"\")\n  write_parquet(p_dt, pth)\n\n  pth <- paste(dir_save, cp, \"-nc-summary.csv\", sep = \"\")\n  write_csv(ncs_df, pth)\n\n  t_stats_df <- fn_transform_t_data(t_dt)\n  pth <- paste(dir_save, cp, \"-average-stats-t.parquet\", sep = \"\")\n  write_parquet(t_stats_df, pth)\n\n  p_stats_df <- fn_transform_p_data(p_dt)\n  pth <- paste(dir_save, cp, \"-average-stats-p.parquet\", sep = \"\")\n  write_parquet(p_stats_df, pth)\n\n  j1_df <- inner_join(t_stats_df, p_stats_df, by = c(\"lon\", \"lat\"))\n  j2_df <- inner_join(j1_df, land_sea_mask_df, by = c(\"lon\", \"lat\"))\n  cn_df <- fn_calc_area(j2_df)\n  pth <- paste(dir_save, cp, \"-climate-normals.parquet\", sep = \"\")\n  write_parquet(cn_df, pth)\n\n}\n\ndir_read <- dir_download\ndir_save <- dir_transform\n\ncp <- \"cpa\"\npth <- paste(dir_save, cp, \"-climate-normals.parquet\", sep = \"\")\n# only need to read, transform, and save if file doesn't exist\nif (!file.exists(pth)) {\n  ncs_df <- fn_create_ncs_df()\n  fn_save_climate_data(dir_read, dir_save, cp, ncs_df) \n}\n\ncp <- \"crp\"\npth <- paste(dir_save, cp, \"-climate-normals.parquet\", sep = \"\")\n# only need to read, transform, and save if file doesn't exist\nif (!file.exists(pth)) {\n  ncs_df <- fn_create_ncs_df()\n  fn_save_climate_data(dir_read, dir_save, cp, ncs_df)  \n}\n\n```\n"},"formats":{"html":{"identifier":{"display-name":"HTML","target-format":"html","base-format":"html"},"execute":{"fig-width":7,"fig-height":5,"fig-format":"retina","fig-dpi":96,"df-print":"default","error":false,"eval":true,"cache":false,"freeze":"auto","echo":true,"output":true,"warning":false,"include":true,"keep-md":false,"keep-ipynb":false,"ipynb":null,"enabled":null,"daemon":null,"daemon-restart":false,"debug":false,"ipynb-filters":[],"ipynb-shell-interactivity":null,"plotly-connected":true,"message":false,"engine":"knitr"},"render":{"keep-tex":false,"keep-typ":false,"keep-source":false,"keep-hidden":false,"prefer-html":false,"output-divs":true,"output-ext":"html","fig-align":"default","fig-pos":null,"fig-env":null,"code-fold":"show","code-overflow":"scroll","code-link":false,"code-line-numbers":false,"code-tools":true,"tbl-colwidths":"auto","merge-includes":true,"inline-includes":false,"preserve-yaml":false,"latex-auto-mk":true,"latex-auto-install":true,"latex-clean":true,"latex-min-runs":1,"latex-max-runs":10,"latex-makeindex":"makeindex","latex-makeindex-opts":[],"latex-tlmgr-opts":[],"latex-input-paths":[],"latex-output-dir":null,"link-external-icon":false,"link-external-newwindow":false,"self-contained-math":false,"format-resources":[],"notebook-links":true},"pandoc":{"standalone":true,"wrap":"none","default-image-extension":"png","to":"html","number-sections":true,"toc":true,"output-file":"02-transform-data.html"},"language":{"toc-title-document":"Table of contents","toc-title-website":"On this page","related-formats-title":"Other Formats","related-notebooks-title":"Notebooks","source-notebooks-prefix":"Source","other-links-title":"Other Links","code-links-title":"Code Links","launch-dev-container-title":"Launch Dev Container","launch-binder-title":"Launch Binder","article-notebook-label":"Article Notebook","notebook-preview-download":"Download Notebook","notebook-preview-download-src":"Download Source","notebook-preview-back":"Back to Article","manuscript-meca-bundle":"MECA Bundle","section-title-abstract":"Abstract","section-title-appendices":"Appendices","section-title-footnotes":"Footnotes","section-title-references":"References","section-title-reuse":"Reuse","section-title-copyright":"Copyright","section-title-citation":"Citation","appendix-attribution-cite-as":"For attribution, please cite this work as:","appendix-attribution-bibtex":"BibTeX citation:","appendix-view-license":"View License","title-block-author-single":"Author","title-block-author-plural":"Authors","title-block-affiliation-single":"Affiliation","title-block-affiliation-plural":"Affiliations","title-block-published":"Published","title-block-modified":"Modified","title-block-keywords":"Keywords","callout-tip-title":"Tip","callout-note-title":"Note","callout-warning-title":"Warning","callout-important-title":"Important","callout-caution-title":"Caution","code-summary":"Code","code-tools-menu-caption":"Code","code-tools-show-all-code":"Show All Code","code-tools-hide-all-code":"Hide All Code","code-tools-view-source":"View Source","code-tools-source-code":"Source Code","tools-share":"Share","tools-download":"Download","code-line":"Line","code-lines":"Lines","copy-button-tooltip":"Copy to Clipboard","copy-button-tooltip-success":"Copied!","repo-action-links-edit":"Edit this page","repo-action-links-source":"View source","repo-action-links-issue":"Report an issue","back-to-top":"Back to top","search-no-results-text":"No results","search-matching-documents-text":"matching documents","search-copy-link-title":"Copy link to search","search-hide-matches-text":"Hide additional matches","search-more-match-text":"more match in this document","search-more-matches-text":"more matches in this document","search-clear-button-title":"Clear","search-text-placeholder":"","search-detached-cancel-button-title":"Cancel","search-submit-button-title":"Submit","search-label":"Search","toggle-section":"Toggle section","toggle-sidebar":"Toggle sidebar navigation","toggle-dark-mode":"Toggle dark mode","toggle-reader-mode":"Toggle reader mode","toggle-navigation":"Toggle navigation","crossref-fig-title":"Figure","crossref-tbl-title":"Table","crossref-lst-title":"Listing","crossref-thm-title":"Theorem","crossref-lem-title":"Lemma","crossref-cor-title":"Corollary","crossref-prp-title":"Proposition","crossref-cnj-title":"Conjecture","crossref-def-title":"Definition","crossref-exm-title":"Example","crossref-exr-title":"Exercise","crossref-ch-prefix":"Chapter","crossref-apx-prefix":"Appendix","crossref-sec-prefix":"Section","crossref-eq-prefix":"Equation","crossref-lof-title":"List of Figures","crossref-lot-title":"List of Tables","crossref-lol-title":"List of Listings","environment-proof-title":"Proof","environment-remark-title":"Remark","environment-solution-title":"Solution","listing-page-order-by":"Order By","listing-page-order-by-default":"Default","listing-page-order-by-date-asc":"Oldest","listing-page-order-by-date-desc":"Newest","listing-page-order-by-number-desc":"High to Low","listing-page-order-by-number-asc":"Low to High","listing-page-field-date":"Date","listing-page-field-title":"Title","listing-page-field-description":"Description","listing-page-field-author":"Author","listing-page-field-filename":"File Name","listing-page-field-filemodified":"Modified","listing-page-field-subtitle":"Subtitle","listing-page-field-readingtime":"Reading Time","listing-page-field-wordcount":"Word Count","listing-page-field-categories":"Categories","listing-page-minutes-compact":"{0} min","listing-page-category-all":"All","listing-page-no-matches":"No matching items","listing-page-words":"{0} words","listing-page-filter":"Filter","draft":"Draft"},"metadata":{"lang":"en","fig-responsive":true,"quarto-version":"1.7.31","theme":"cosmo","title":"Transform Data"},"extensions":{"book":{"multiFile":true}}}},"projectFormats":["html"]}